xchk_tmux_content/__init__.py
xchk_tmux_content/apps.py
xchk_tmux_content/contentviews.py
xchk_tmux_content/course.py
xchk_tmux_content/static/images
xchk_tmux_content/static/xchk_tmux_content/images/2154f7fa30dc4c7ea48b8f1066e16d7e
xchk_tmux_content/static/xchk_tmux_content/images/2505fae5ccd04e169cacce9d77b92cbb
xchk_tmux_content/static/xchk_tmux_content/images/baa7717e80e04fb2ae411e159fe4be0d
xchk_tmux_content/static/xchk_tmux_content/images/ce6d30d4d28a40068f5de7ee521c0c54
xchk_tmux_content/strats.py
xchk_tmux_content/templates/xchk_tmux_content/al_dan_niet_bestaande_sessie_gebruiken.html
xchk_tmux_content/templates/xchk_tmux_content/basis_pair_programming.html
xchk_tmux_content/templates/xchk_tmux_content/beeindigen_van_een_bestaande_sessie.html
xchk_tmux_content/templates/xchk_tmux_content/buffer_doorzoeken.html
xchk_tmux_content/templates/xchk_tmux_content/buffer_stack.html
xchk_tmux_content/templates/xchk_tmux_content/command_delay.html
xchk_tmux_content/templates/xchk_tmux_content/command_in_meerdere_panes_uitvoeren.html
xchk_tmux_content/templates/xchk_tmux_content/command_mode_activeren.html
xchk_tmux_content/templates/xchk_tmux_content/command_prefix.html
xchk_tmux_content/templates/xchk_tmux_content/configuratie_kleuren.html
xchk_tmux_content/templates/xchk_tmux_content/copy_buffer_opslaan.html
xchk_tmux_content/templates/xchk_tmux_content/copy_mode_key_table.html
xchk_tmux_content/templates/xchk_tmux_content/custom_configuratiefile_gebruiken.html
xchk_tmux_content/templates/xchk_tmux_content/door_output_scrollen_copy_mode.html
xchk_tmux_content/templates/xchk_tmux_content/een_volledig_pane_kopieren.html
xchk_tmux_content/templates/xchk_tmux_content/grouped_sessions.html
xchk_tmux_content/templates/xchk_tmux_content/hooks.html
xchk_tmux_content/templates/xchk_tmux_content/indexen_voor_windows_en_panes_instellen.html
xchk_tmux_content/templates/xchk_tmux_content/ingebouwde_pane_layouts_gebruiken.html
xchk_tmux_content-0.0.2.dist-info/WHEEL
xchk_tmux_content-0.0.2.dist-info/METADATA
xchk_tmux_content-0.0.2.dist-info/RECORD
