Metadata-Version: 2.1
Name: xchk-tmux-content
Version: 0.0.2
Summary: Course material related to tmux for the xchk teaching framework
License: MIT
Author: Vincent Nys
Author-email: vincentnys@gmail.com
Requires-Python: >=3.7,<4.0
Classifier: License :: OSI Approved :: MIT License
Classifier: Programming Language :: Python :: 3
Classifier: Programming Language :: Python :: 3.7
Classifier: Programming Language :: Python :: 3.8
Classifier: Programming Language :: Python :: 3.9
